report_race/__init__.py
report_race/constant.py
report_race/race.py
report_race/report.py
report_race-0.1.0.dist-info/METADATA
report_race-0.1.0.dist-info/WHEEL
report_race-0.1.0.dist-info/licenses/LICENSE
report_race-0.1.0.dist-info/RECORD
