Metadata-Version: 2.1
Name: report_race
Version: 0.1.0
Summary: Cli for report of Monaco race.
Author-email: Svjatoslav Matvejev <svjatoslav.matvejev@gmail.com>
License-File: LICENSE
Keywords: report
Classifier: License :: OSI Approved :: MIT License
Classifier: Operating System :: OS Independent
Classifier: Programming Language :: Python :: 3.9
Requires-Python: >=3.9
Requires-Dist: tabulate==0.9.0
